finergy_mia_pos_sdk/__init__.py
finergy_mia_pos_sdk/finergy_mia_pos_api_client.py
finergy_mia_pos_sdk/finergy_mia_pos_auth_client.py
finergy_mia_pos_sdk/finergy_mia_pos_common.py
finergy_mia_pos_sdk/finergy_mia_pos_sdk.py
finergy_mia_pos_sdk-1.1.3.dist-info/licenses/LICENSE
finergy_mia_pos_sdk-1.1.3.dist-info/METADATA
finergy_mia_pos_sdk-1.1.3.dist-info/WHEEL
finergy_mia_pos_sdk-1.1.3.dist-info/top_level.txt
finergy_mia_pos_sdk-1.1.3.dist-info/RECORD
