Metadata-Version: 2.4
Name: finergy-mia-pos-sdk
Version: 1.1.3
Summary: Python SDK for Finergy MIA POS eComm API
Author: Alexander Minza
License-Expression: GPL-3.0-or-later
Project-URL: Homepage, https://github.com/alexminza/finergy-mia-pos-sdk-python
Project-URL: Issues, https://github.com/alexminza/finergy-mia-pos-sdk-python/issues
Project-URL: Repository, https://github.com/alexminza/finergy-mia-pos-sdk-python
Project-URL: Documentation, https://github.com/finergy-tech/mia-pay-ecomm-integration
Keywords: finergy,moldova,mia,pos,qr,payments,api,sdk,python
Classifier: Intended Audience :: Developers
Classifier: Operating System :: OS Independent
Classifier: Programming Language :: Python :: 3
Classifier: Topic :: Software Development :: Libraries :: Python Modules
Requires-Python: >=3.9
License-File: LICENSE
Requires-Dist: httpx
Requires-Dist: cryptography
Dynamic: license-file
